encodapy/__init__.py
encodapy/components/__init__.py
encodapy/components/basic_component.py
encodapy/components/basic_component_config.py
encodapy/components/component_loader.py
encodapy/components/readme.md
encodapy/components/thermal_storage/__init__.py
encodapy/components/thermal_storage/readme.md
encodapy/components/thermal_storage/thermal_storage.py
encodapy/components/thermal_storage/thermal_storage_config.py
encodapy/components/two_point_controller/__init__.py
encodapy/components/two_point_controller/readme.md
encodapy/components/two_point_controller/two_point_controller.py
encodapy/components/two_point_controller/two_point_controller_config.py
encodapy/config/__init__.py
encodapy/config/env_values.py
encodapy/config/models.py
encodapy/config/mqtt_messages_template.py
encodapy/config/types.py
encodapy/py.typed
encodapy/service/__init__.py
encodapy/service/basic_service.py
encodapy/service/communication/__init__.py
encodapy/service/communication/file_connection.py
encodapy/service/communication/fiware_connection.py
encodapy/service/communication/mqtt_connection.py
encodapy/service/component_runner_service.py
encodapy/service/service_main.py
encodapy/utils/cratedb.py
encodapy/utils/datapoints.py
encodapy/utils/error_handling.py
encodapy/utils/fiware_auth.py
encodapy/utils/health.py
encodapy/utils/logging.py
encodapy/utils/mediums.py
encodapy/utils/models.py
encodapy/utils/units.py
encodapy-0.7.0.dist-info/METADATA
encodapy-0.7.0.dist-info/WHEEL
encodapy-0.7.0.dist-info/licenses/LICENSE
encodapy-0.7.0.dist-info/RECORD
