Metadata-Version: 2.4
Name: encodapy
Version: 0.7.0
Summary: EnCoDaPy – Energy Control and Data Preparation in Python.
License: BSD-3-Clause
License-File: LICENSE
Author: Martin Altenburger
Author-email: martin.altenburger@tu-dresden.de
Requires-Python: >=3.11,<3.13
Classifier: License :: OSI Approved :: BSD License
Classifier: Programming Language :: Python :: 3
Classifier: Programming Language :: Python :: 3.11
Classifier: Programming Language :: Python :: 3.12
Requires-Dist: crate (>=0.31.1)
Requires-Dist: filip (>=0.7.0)
Requires-Dist: loguru (>=0.6.0)
Requires-Dist: nbformat (>=5.7.1)
Requires-Dist: numpy (>=1.23.5)
Requires-Dist: pandas (>=2.1.4,<=2.3.1)
Requires-Dist: pydantic (>=2.5.2,<2.7.0)
Requires-Dist: pydantic-settings (>=2.2.1,<3.0.0)
Requires-Dist: python-dotenv (>=1.0.1)
Requires-Dist: requests (>=2.31.0)
Requires-Dist: requests-oauthlib (>=1.3.1)
Requires-Dist: statsmodels (>=0.14.4)
Requires-Dist: types-requests (>=2.32.4,<3.0.0)
Project-URL: Documentation, https://gewv-tu-dresden.github.io/encodapy/
Project-URL: Repository, https://github.com/gewv-tu-dresden/encodapy
